explicit_agent/__init__.py
explicit_agent/agent.py
explicit_agent/tools.py
explicit_agent-0.2.1.dist-info/LICENSE
explicit_agent-0.2.1.dist-info/METADATA
explicit_agent-0.2.1.dist-info/WHEEL
explicit_agent-0.2.1.dist-info/top_level.txt
explicit_agent-0.2.1.dist-info/RECORD
