Metadata-Version: 2.2
Name: explicit-agent
Version: 0.2.1
Summary: A simple framework for creating transparent tool-using agents
Author-email: Gabri Ansaldo <ansaldo.gabri@gmail.com>
Project-URL: Homepage, https://github.com/gabriansa/explicit-agent
Project-URL: Bug Tracker, https://github.com/gabriansa/explicit-agent/issues
Classifier: Programming Language :: Python :: 3
Classifier: License :: OSI Approved :: MIT License
Classifier: Operating System :: OS Independent
Requires-Python: >=3.9
License-File: LICENSE
Requires-Dist: openai>=1.0.0
Requires-Dist: pydantic>=2.0.0
Requires-Dist: rich>=12.0.0
